xia_models/__init__.py
xia_models/address.cpython-311-darwin.so
xia_models/model.cpython-311-darwin.so
xia_models-0.1.11.dist-info/LICENSE.txt
xia_models-0.1.11.dist-info/METADATA
xia_models-0.1.11.dist-info/WHEEL
xia_models-0.1.11.dist-info/top_level.txt
xia_models-0.1.11.dist-info/RECORD
